examples/common.py
examples/mirror.py
examples/video.py
tests/test_throttle.py
wincam/__init__.py
wincam/camera.py
wincam/desktop.py
wincam/dxcam.py
wincam/logger.py
wincam/native.py
wincam/throttle.py
wincam/timer.py
wincam/native/runtimes/x64/ScreenCapture.dll
wincam/native/runtimes/x64/ScreenCapture.exp
wincam/native/runtimes/x64/ScreenCapture.lib
wincam/native/runtimes/x64/ScreenCapture.pdb
wincam/native/runtimes/x64/avcodec-61.dll
wincam/native/runtimes/x64/avdevice-61.dll
wincam/native/runtimes/x64/avfilter-10.dll
wincam/native/runtimes/x64/avformat-61.dll
wincam/native/runtimes/x64/avutil-59.dll
wincam/native/runtimes/x64/postproc-58.dll
wincam/native/runtimes/x64/swresample-5.dll
wincam/native/runtimes/x64/swscale-8.dll
wincam-1.0.14.dist-info/licenses/LICENSE
wincam-1.0.14.dist-info/METADATA
wincam-1.0.14.dist-info/WHEEL
wincam-1.0.14.dist-info/top_level.txt
wincam-1.0.14.dist-info/RECORD
