Metadata-Version: 2.4
Name: wincam
Version: 1.0.14
Summary: A Python high-performance screenshot library for Windows 10+ using Direct3D11CaptureFramePool.
Author: lovettchris
Project-URL: Homepage, https://github.com/lovettchris/wincam
Project-URL: Issues, https://github.com/lovettchris/wincam/issues
Classifier: Intended Audience :: Developers
Classifier: Programming Language :: Python :: 3
Classifier: License :: OSI Approved :: MIT License
Classifier: Operating System :: Microsoft :: Windows :: Windows 10
Classifier: Operating System :: Microsoft :: Windows :: Windows 11
Classifier: Topic :: Multimedia :: Graphics
Classifier: Topic :: Multimedia :: Graphics :: Capture
Classifier: Topic :: Multimedia :: Graphics :: Capture :: Screen Capture
Requires-Python: >=3.10
License-File: LICENSE
Requires-Dist: opencv-contrib-python
Requires-Dist: numpy
Requires-Dist: pywin32; sys_platform == "win32"
Provides-Extra: dev
Requires-Dist: build; extra == "dev"
Requires-Dist: black; extra == "dev"
Requires-Dist: isort; extra == "dev"
Requires-Dist: flake8; extra == "dev"
Requires-Dist: Flake8-pyproject; extra == "dev"
Requires-Dist: mypy; extra == "dev"
Requires-Dist: mypy-extensions; extra == "dev"
Requires-Dist: types-PyYAML; extra == "dev"
Requires-Dist: twine; extra == "dev"
Provides-Extra: test
Requires-Dist: pytest==7.3.1; extra == "test"
Provides-Extra: all
Requires-Dist: wincam[dev,test]; extra == "all"
Dynamic: license-file
